{
  "apiVersion": "kubevirt.io/v1",
  "kind": "VirtualMachineInstanceMigration",
  "metadata": {
    "annotations": {
      "kubevirt.io/evacuationMigration": "d23-h29-000-r650",
      "kubevirt.io/latest-observed-api-version": "v1",
      "kubevirt.io/storage-observed-api-version": "v1"
    },
    "creationTimestamp": "2025-11-20T09:32:28Z",
    "generateName": "kubevirt-evacuation-",
    "generation": 1,
    "labels": {
      "kubevirt.io/vmi-name": "rhel9-9941"
    },
    "name": "kubevirt-evacuation-fnpf9",
    "namespace": "vm-ns-15",
    "resourceVersion": "381990904",
    "uid": "6a757fa7-1620-4b58-9036-774c1a8f4eae"
  },
  "spec": {
    "vmiName": "rhel9-9941"
  },
  "status": {
    "migrationState": {
      "completed": true,
      "endTimestamp": "2025-11-20T09:33:02Z",
      "migrationConfiguration": {
        "allowAutoConverge": false,
        "allowPostCopy": false,
        "allowWorkloadDisruption": false,
        "bandwidthPerMigration": "0",
        "completionTimeoutPerGiB": 150,
        "nodeDrainTaintKey": "kubevirt.io/drain",
        "parallelMigrationsPerCluster": 50,
        "parallelOutboundMigrationsPerNode": 10,
        "progressTimeout": 150,
        "unsafeMigrationOverride": false
      },
      "migrationUid": "6a757fa7-1620-4b58-9036-774c1a8f4eae",
      "mode": "PreCopy",
      "sourceNode": "d23-h29-000-r650",
      "sourcePod": "virt-launcher-rhel9-9941-tr4b2",
      "startTimestamp": "2025-11-20T09:32:53Z",
      "targetDirectMigrationNodePorts": {
        "35905": 0,
        "39307": 49152
      },
      "targetNode": "d23-h24-000-r650",
      "targetNodeAddress": "10.131.26.125",
      "targetNodeDomainDetected": true,
      "targetNodeDomainReadyTimestamp": "2025-11-20T09:33:02Z",
      "targetPod": "virt-launcher-rhel9-9941-b2dpc"
    },
    "phase": "Succeeded",
    "phaseTransitionTimestamps": [
      {
        "phase": "Pending",
        "phaseTransitionTimestamp": "2025-11-20T09:32:29Z"
      },
      {
        "phase": "Scheduling",
        "phaseTransitionTimestamp": "2025-11-20T09:32:39Z"
      },
      {
        "phase": "Scheduled",
        "phaseTransitionTimestamp": "2025-11-20T09:32:53Z"
      },
      {
        "phase": "PreparingTarget",
        "phaseTransitionTimestamp": "2025-11-20T09:32:53Z"
      },
      {
        "phase": "TargetReady",
        "phaseTransitionTimestamp": "2025-11-20T09:32:53Z"
      },
      {
        "phase": "Running",
        "phaseTransitionTimestamp": "2025-11-20T09:32:53Z"
      },
      {
        "phase": "Succeeded",
        "phaseTransitionTimestamp": "2025-11-20T09:33:02Z"
      }
    ]
  }
}
