{
  "apiVersion": "kubevirt.io/v1",
  "kind": "VirtualMachineInstanceMigration",
  "metadata": {
    "annotations": {
      "kubevirt.io/evacuationMigration": "e45-h05-000-r650",
      "kubevirt.io/latest-observed-api-version": "v1",
      "kubevirt.io/storage-observed-api-version": "v1"
    },
    "creationTimestamp": "2025-11-21T00:13:01Z",
    "generateName": "kubevirt-evacuation-",
    "generation": 1,
    "labels": {
      "kubevirt.io/vmi-name": "rhel9-13314"
    },
    "name": "kubevirt-evacuation-22xt7",
    "namespace": "vm-ns-20",
    "resourceVersion": "390634628",
    "uid": "f30eaf86-2012-4e80-a5e7-1a7fb5c8fdf1"
  },
  "spec": {
    "vmiName": "rhel9-13314"
  },
  "status": {
    "migrationState": {
      "completed": true,
      "endTimestamp": "2025-11-21T00:20:24Z",
      "migrationConfiguration": {
        "allowAutoConverge": false,
        "allowPostCopy": false,
        "allowWorkloadDisruption": false,
        "bandwidthPerMigration": "0",
        "completionTimeoutPerGiB": 150,
        "nodeDrainTaintKey": "kubevirt.io/drain",
        "parallelMigrationsPerCluster": 50,
        "parallelOutboundMigrationsPerNode": 10,
        "progressTimeout": 150,
        "unsafeMigrationOverride": false
      },
      "migrationUid": "f30eaf86-2012-4e80-a5e7-1a7fb5c8fdf1",
      "mode": "PreCopy",
      "sourceNode": "e45-h05-000-r650",
      "sourcePod": "virt-launcher-rhel9-13314-mmgj6",
      "startTimestamp": "2025-11-21T00:20:15Z",
      "targetDirectMigrationNodePorts": {
        "33131": 0,
        "35107": 49152
      },
      "targetNode": "e34-h03-000-r650",
      "targetNodeAddress": "10.131.58.69",
      "targetNodeDomainDetected": true,
      "targetNodeDomainReadyTimestamp": "2025-11-21T00:20:24Z",
      "targetPod": "virt-launcher-rhel9-13314-8gqqb"
    },
    "phase": "Succeeded",
    "phaseTransitionTimestamps": [
      {
        "phase": "Pending",
        "phaseTransitionTimestamp": "2025-11-21T00:13:01Z"
      },
      {
        "phase": "Scheduling",
        "phaseTransitionTimestamp": "2025-11-21T00:20:03Z"
      },
      {
        "phase": "Scheduled",
        "phaseTransitionTimestamp": "2025-11-21T00:20:15Z"
      },
      {
        "phase": "PreparingTarget",
        "phaseTransitionTimestamp": "2025-11-21T00:20:15Z"
      },
      {
        "phase": "TargetReady",
        "phaseTransitionTimestamp": "2025-11-21T00:20:15Z"
      },
      {
        "phase": "Running",
        "phaseTransitionTimestamp": "2025-11-21T00:20:15Z"
      },
      {
        "phase": "Succeeded",
        "phaseTransitionTimestamp": "2025-11-21T00:20:24Z"
      }
    ]
  }
}
