{
  "apiVersion": "kubevirt.io/v1",
  "kind": "VirtualMachineInstanceMigration",
  "metadata": {
    "annotations": {
      "kubevirt.io/evacuationMigration": "e28-h25-000-r650",
      "kubevirt.io/latest-observed-api-version": "v1",
      "kubevirt.io/storage-observed-api-version": "v1"
    },
    "creationTimestamp": "2025-11-20T18:47:24Z",
    "generateName": "kubevirt-evacuation-",
    "generation": 1,
    "labels": {
      "kubevirt.io/vmi-name": "rhel9-12866"
    },
    "name": "kubevirt-evacuation-wql2k",
    "namespace": "vm-ns-19",
    "resourceVersion": "384143213",
    "uid": "f986ca44-9bbf-474e-b91e-6bb80ea38409"
  },
  "spec": {
    "vmiName": "rhel9-12866"
  },
  "status": {
    "migrationState": {
      "completed": true,
      "endTimestamp": "2025-11-20T18:47:49Z",
      "migrationConfiguration": {
        "allowAutoConverge": false,
        "allowPostCopy": false,
        "allowWorkloadDisruption": false,
        "bandwidthPerMigration": "0",
        "completionTimeoutPerGiB": 150,
        "nodeDrainTaintKey": "kubevirt.io/drain",
        "parallelMigrationsPerCluster": 50,
        "parallelOutboundMigrationsPerNode": 10,
        "progressTimeout": 150,
        "unsafeMigrationOverride": false
      },
      "migrationUid": "f986ca44-9bbf-474e-b91e-6bb80ea38409",
      "mode": "PreCopy",
      "sourceNode": "e28-h25-000-r650",
      "sourcePod": "virt-launcher-rhel9-12866-jtqwb",
      "startTimestamp": "2025-11-20T18:47:40Z",
      "targetDirectMigrationNodePorts": {
        "36439": 0,
        "38235": 49152
      },
      "targetNode": "e28-h14-000-r650",
      "targetNodeAddress": "10.128.12.139",
      "targetNodeDomainDetected": true,
      "targetNodeDomainReadyTimestamp": "2025-11-20T18:47:49Z",
      "targetPod": "virt-launcher-rhel9-12866-7rf25"
    },
    "phase": "Succeeded",
    "phaseTransitionTimestamps": [
      {
        "phase": "Pending",
        "phaseTransitionTimestamp": "2025-11-20T18:47:24Z"
      },
      {
        "phase": "Scheduling",
        "phaseTransitionTimestamp": "2025-11-20T18:47:34Z"
      },
      {
        "phase": "Scheduled",
        "phaseTransitionTimestamp": "2025-11-20T18:47:40Z"
      },
      {
        "phase": "PreparingTarget",
        "phaseTransitionTimestamp": "2025-11-20T18:47:40Z"
      },
      {
        "phase": "TargetReady",
        "phaseTransitionTimestamp": "2025-11-20T18:47:40Z"
      },
      {
        "phase": "Running",
        "phaseTransitionTimestamp": "2025-11-20T18:47:40Z"
      },
      {
        "phase": "Succeeded",
        "phaseTransitionTimestamp": "2025-11-20T18:47:49Z"
      }
    ]
  }
}
