{
  "apiVersion": "kubevirt.io/v1",
  "kind": "VirtualMachineInstanceMigration",
  "metadata": {
    "annotations": {
      "kubevirt.io/evacuationMigration": "e44-h36-000-r650",
      "kubevirt.io/latest-observed-api-version": "v1",
      "kubevirt.io/storage-observed-api-version": "v1"
    },
    "creationTimestamp": "2025-11-20T23:39:13Z",
    "generateName": "kubevirt-evacuation-",
    "generation": 1,
    "labels": {
      "kubevirt.io/vmi-name": "rhel9-12643"
    },
    "name": "kubevirt-evacuation-ttlgx",
    "namespace": "vm-ns-19",
    "resourceVersion": "389630268",
    "uid": "f919c5d9-45a8-445c-9d62-bff69d3cdcaf"
  },
  "spec": {
    "vmiName": "rhel9-12643"
  },
  "status": {
    "migrationState": {
      "completed": true,
      "endTimestamp": "2025-11-20T23:41:38Z",
      "migrationConfiguration": {
        "allowAutoConverge": false,
        "allowPostCopy": false,
        "allowWorkloadDisruption": false,
        "bandwidthPerMigration": "0",
        "completionTimeoutPerGiB": 150,
        "nodeDrainTaintKey": "kubevirt.io/drain",
        "parallelMigrationsPerCluster": 50,
        "parallelOutboundMigrationsPerNode": 10,
        "progressTimeout": 150,
        "unsafeMigrationOverride": false
      },
      "migrationUid": "f919c5d9-45a8-445c-9d62-bff69d3cdcaf",
      "mode": "PreCopy",
      "sourceNode": "e44-h36-000-r650",
      "sourcePod": "virt-launcher-rhel9-12643-g55xf",
      "startTimestamp": "2025-11-20T23:41:32Z",
      "targetDirectMigrationNodePorts": {
        "36713": 49152,
        "44103": 0
      },
      "targetNode": "e44-h34-000-r650",
      "targetNodeAddress": "10.131.70.133",
      "targetNodeDomainDetected": true,
      "targetNodeDomainReadyTimestamp": "2025-11-20T23:41:38Z",
      "targetPod": "virt-launcher-rhel9-12643-mwbhl"
    },
    "phase": "Succeeded",
    "phaseTransitionTimestamps": [
      {
        "phase": "Pending",
        "phaseTransitionTimestamp": "2025-11-20T23:39:13Z"
      },
      {
        "phase": "Scheduling",
        "phaseTransitionTimestamp": "2025-11-20T23:41:25Z"
      },
      {
        "phase": "Scheduled",
        "phaseTransitionTimestamp": "2025-11-20T23:41:32Z"
      },
      {
        "phase": "PreparingTarget",
        "phaseTransitionTimestamp": "2025-11-20T23:41:32Z"
      },
      {
        "phase": "TargetReady",
        "phaseTransitionTimestamp": "2025-11-20T23:41:32Z"
      },
      {
        "phase": "Running",
        "phaseTransitionTimestamp": "2025-11-20T23:41:32Z"
      },
      {
        "phase": "Succeeded",
        "phaseTransitionTimestamp": "2025-11-20T23:41:38Z"
      }
    ]
  }
}
