{
  "apiVersion": "kubevirt.io/v1",
  "kind": "VirtualMachineInstanceMigration",
  "metadata": {
    "annotations": {
      "kubevirt.io/evacuationMigration": "d21-h24-000-r650",
      "kubevirt.io/latest-observed-api-version": "v1",
      "kubevirt.io/storage-observed-api-version": "v1"
    },
    "creationTimestamp": "2025-11-20T07:45:26Z",
    "generateName": "kubevirt-evacuation-",
    "generation": 1,
    "labels": {
      "kubevirt.io/vmi-name": "rhel9-13150"
    },
    "name": "kubevirt-evacuation-plbds",
    "namespace": "vm-ns-19",
    "resourceVersion": "381547412",
    "uid": "05b99029-6438-4184-983e-91ee1c7638b8"
  },
  "spec": {
    "vmiName": "rhel9-13150"
  },
  "status": {
    "migrationState": {
      "completed": true,
      "endTimestamp": "2025-11-20T07:45:47Z",
      "migrationConfiguration": {
        "allowAutoConverge": false,
        "allowPostCopy": false,
        "allowWorkloadDisruption": false,
        "bandwidthPerMigration": "0",
        "completionTimeoutPerGiB": 150,
        "nodeDrainTaintKey": "kubevirt.io/drain",
        "parallelMigrationsPerCluster": 50,
        "parallelOutboundMigrationsPerNode": 10,
        "progressTimeout": 150,
        "unsafeMigrationOverride": false
      },
      "migrationUid": "05b99029-6438-4184-983e-91ee1c7638b8",
      "mode": "PreCopy",
      "sourceNode": "d21-h24-000-r650",
      "sourcePod": "virt-launcher-rhel9-13150-chv78",
      "startTimestamp": "2025-11-20T07:45:36Z",
      "targetDirectMigrationNodePorts": {
        "42489": 49152,
        "46877": 0
      },
      "targetNode": "d20-h15-000-r650",
      "targetNodeAddress": "10.129.18.126",
      "targetNodeDomainDetected": true,
      "targetNodeDomainReadyTimestamp": "2025-11-20T07:45:47Z",
      "targetPod": "virt-launcher-rhel9-13150-vbbdg"
    },
    "phase": "Succeeded",
    "phaseTransitionTimestamps": [
      {
        "phase": "Pending",
        "phaseTransitionTimestamp": "2025-11-20T07:45:26Z"
      },
      {
        "phase": "Scheduling",
        "phaseTransitionTimestamp": "2025-11-20T07:45:26Z"
      },
      {
        "phase": "Scheduled",
        "phaseTransitionTimestamp": "2025-11-20T07:45:36Z"
      },
      {
        "phase": "PreparingTarget",
        "phaseTransitionTimestamp": "2025-11-20T07:45:36Z"
      },
      {
        "phase": "TargetReady",
        "phaseTransitionTimestamp": "2025-11-20T07:45:36Z"
      },
      {
        "phase": "Running",
        "phaseTransitionTimestamp": "2025-11-20T07:45:36Z"
      },
      {
        "phase": "Succeeded",
        "phaseTransitionTimestamp": "2025-11-20T07:45:47Z"
      }
    ]
  }
}
