{
  "apiVersion": "kubevirt.io/v1",
  "kind": "VirtualMachineInstanceMigration",
  "metadata": {
    "annotations": {
      "kubevirt.io/evacuationMigration": "d24-h02-000-r650",
      "kubevirt.io/latest-observed-api-version": "v1",
      "kubevirt.io/storage-observed-api-version": "v1"
    },
    "creationTimestamp": "2025-11-21T06:19:21Z",
    "generateName": "kubevirt-evacuation-",
    "generation": 1,
    "labels": {
      "kubevirt.io/vmi-name": "rhel9-7982"
    },
    "name": "kubevirt-evacuation-z7th8",
    "namespace": "vm-ns-12",
    "resourceVersion": "399544920",
    "uid": "14d825d8-d7fa-4230-833a-400a7d28c83b"
  },
  "spec": {
    "vmiName": "rhel9-7982"
  },
  "status": {
    "migrationState": {
      "completed": true,
      "endTimestamp": "2025-11-21T06:19:59Z",
      "migrationConfiguration": {
        "allowAutoConverge": false,
        "allowPostCopy": false,
        "allowWorkloadDisruption": false,
        "bandwidthPerMigration": "0",
        "completionTimeoutPerGiB": 150,
        "nodeDrainTaintKey": "kubevirt.io/drain",
        "parallelMigrationsPerCluster": 50,
        "parallelOutboundMigrationsPerNode": 10,
        "progressTimeout": 150,
        "unsafeMigrationOverride": false
      },
      "migrationUid": "14d825d8-d7fa-4230-833a-400a7d28c83b",
      "mode": "PreCopy",
      "sourceNode": "d24-h02-000-r650",
      "sourcePod": "virt-launcher-rhel9-7982-ljhmq",
      "startTimestamp": "2025-11-21T06:19:28Z",
      "targetDirectMigrationNodePorts": {
        "33935": 49152,
        "39823": 0
      },
      "targetNode": "d40-h12-000-r660",
      "targetNodeAddress": "10.131.90.124",
      "targetNodeDomainDetected": true,
      "targetNodeDomainReadyTimestamp": "2025-11-21T06:19:58Z",
      "targetPod": "virt-launcher-rhel9-7982-fzx4g"
    },
    "phase": "Succeeded",
    "phaseTransitionTimestamps": [
      {
        "phase": "Pending",
        "phaseTransitionTimestamp": "2025-11-21T06:19:21Z"
      },
      {
        "phase": "Scheduling",
        "phaseTransitionTimestamp": "2025-11-21T06:19:21Z"
      },
      {
        "phase": "Scheduled",
        "phaseTransitionTimestamp": "2025-11-21T06:19:28Z"
      },
      {
        "phase": "PreparingTarget",
        "phaseTransitionTimestamp": "2025-11-21T06:19:28Z"
      },
      {
        "phase": "TargetReady",
        "phaseTransitionTimestamp": "2025-11-21T06:19:28Z"
      },
      {
        "phase": "Running",
        "phaseTransitionTimestamp": "2025-11-21T06:19:28Z"
      },
      {
        "phase": "Succeeded",
        "phaseTransitionTimestamp": "2025-11-21T06:19:59Z"
      }
    ]
  }
}
