{
  "apiVersion": "kubevirt.io/v1",
  "kind": "VirtualMachineInstanceMigration",
  "metadata": {
    "annotations": {
      "kubevirt.io/evacuationMigration": "e43-h01-000-r650",
      "kubevirt.io/latest-observed-api-version": "v1",
      "kubevirt.io/storage-observed-api-version": "v1"
    },
    "creationTimestamp": "2025-11-20T23:01:35Z",
    "generateName": "kubevirt-evacuation-",
    "generation": 1,
    "labels": {
      "kubevirt.io/vmi-name": "rhel9-8246"
    },
    "name": "kubevirt-evacuation-jkzrv",
    "namespace": "vm-ns-12",
    "resourceVersion": "388615006",
    "uid": "2fcdbe63-c773-496d-bc32-d5bf7510fd88"
  },
  "spec": {
    "vmiName": "rhel9-8246"
  },
  "status": {
    "migrationState": {
      "completed": true,
      "endTimestamp": "2025-11-20T23:02:03Z",
      "migrationConfiguration": {
        "allowAutoConverge": false,
        "allowPostCopy": false,
        "allowWorkloadDisruption": false,
        "bandwidthPerMigration": "0",
        "completionTimeoutPerGiB": 150,
        "nodeDrainTaintKey": "kubevirt.io/drain",
        "parallelMigrationsPerCluster": 50,
        "parallelOutboundMigrationsPerNode": 10,
        "progressTimeout": 150,
        "unsafeMigrationOverride": false
      },
      "migrationUid": "2fcdbe63-c773-496d-bc32-d5bf7510fd88",
      "mode": "PreCopy",
      "sourceNode": "e43-h01-000-r650",
      "sourcePod": "virt-launcher-rhel9-8246-jbm8m",
      "startTimestamp": "2025-11-20T23:01:52Z",
      "targetDirectMigrationNodePorts": {
        "39497": 0,
        "41785": 49152
      },
      "targetNode": "e42-h37-000-r650",
      "targetNodeAddress": "10.131.68.143",
      "targetNodeDomainDetected": true,
      "targetNodeDomainReadyTimestamp": "2025-11-20T23:02:03Z",
      "targetPod": "virt-launcher-rhel9-8246-mn4b7"
    },
    "phase": "Succeeded",
    "phaseTransitionTimestamps": [
      {
        "phase": "Pending",
        "phaseTransitionTimestamp": "2025-11-20T23:01:39Z"
      },
      {
        "phase": "Scheduling",
        "phaseTransitionTimestamp": "2025-11-20T23:01:46Z"
      },
      {
        "phase": "Scheduled",
        "phaseTransitionTimestamp": "2025-11-20T23:01:52Z"
      },
      {
        "phase": "PreparingTarget",
        "phaseTransitionTimestamp": "2025-11-20T23:01:52Z"
      },
      {
        "phase": "TargetReady",
        "phaseTransitionTimestamp": "2025-11-20T23:01:52Z"
      },
      {
        "phase": "Running",
        "phaseTransitionTimestamp": "2025-11-20T23:01:52Z"
      },
      {
        "phase": "Succeeded",
        "phaseTransitionTimestamp": "2025-11-20T23:02:03Z"
      }
    ]
  }
}
