{
  "apiVersion": "kubevirt.io/v1",
  "kind": "VirtualMachineInstanceMigration",
  "metadata": {
    "annotations": {
      "kubevirt.io/evacuationMigration": "e37-h07-000-r650",
      "kubevirt.io/latest-observed-api-version": "v1",
      "kubevirt.io/storage-observed-api-version": "v1"
    },
    "creationTimestamp": "2025-11-20T18:52:06Z",
    "generateName": "kubevirt-evacuation-",
    "generation": 1,
    "labels": {
      "kubevirt.io/vmi-name": "rhel9-1024"
    },
    "name": "kubevirt-evacuation-qfm46",
    "namespace": "vm-ns-2",
    "resourceVersion": "384167639",
    "uid": "629f3d5b-1319-4a4b-aef2-fd4abb1c65c1"
  },
  "spec": {
    "vmiName": "rhel9-1024"
  },
  "status": {
    "migrationState": {
      "completed": true,
      "endTimestamp": "2025-11-20T18:52:42Z",
      "migrationConfiguration": {
        "allowAutoConverge": false,
        "allowPostCopy": false,
        "allowWorkloadDisruption": false,
        "bandwidthPerMigration": "0",
        "completionTimeoutPerGiB": 150,
        "nodeDrainTaintKey": "kubevirt.io/drain",
        "parallelMigrationsPerCluster": 50,
        "parallelOutboundMigrationsPerNode": 10,
        "progressTimeout": 150,
        "unsafeMigrationOverride": false
      },
      "migrationUid": "629f3d5b-1319-4a4b-aef2-fd4abb1c65c1",
      "mode": "PreCopy",
      "sourceNode": "e37-h07-000-r650",
      "sourcePod": "virt-launcher-rhel9-1024-bv4tz",
      "startTimestamp": "2025-11-20T18:52:21Z",
      "targetDirectMigrationNodePorts": {
        "38195": 0,
        "43953": 49152
      },
      "targetNode": "e28-h18-000-r650",
      "targetNodeAddress": "10.129.12.127",
      "targetNodeDomainDetected": true,
      "targetNodeDomainReadyTimestamp": "2025-11-20T18:52:42Z",
      "targetPod": "virt-launcher-rhel9-1024-c4r99"
    },
    "phase": "Succeeded",
    "phaseTransitionTimestamps": [
      {
        "phase": "Pending",
        "phaseTransitionTimestamp": "2025-11-20T18:52:06Z"
      },
      {
        "phase": "Scheduling",
        "phaseTransitionTimestamp": "2025-11-20T18:52:06Z"
      },
      {
        "phase": "Scheduled",
        "phaseTransitionTimestamp": "2025-11-20T18:52:21Z"
      },
      {
        "phase": "PreparingTarget",
        "phaseTransitionTimestamp": "2025-11-20T18:52:21Z"
      },
      {
        "phase": "TargetReady",
        "phaseTransitionTimestamp": "2025-11-20T18:52:21Z"
      },
      {
        "phase": "Running",
        "phaseTransitionTimestamp": "2025-11-20T18:52:21Z"
      },
      {
        "phase": "Succeeded",
        "phaseTransitionTimestamp": "2025-11-20T18:52:42Z"
      }
    ]
  }
}
