{
  "apiVersion": "kubevirt.io/v1",
  "kind": "VirtualMachineInstanceMigration",
  "metadata": {
    "annotations": {
      "kubevirt.io/evacuationMigration": "d24-h01-000-r650",
      "kubevirt.io/latest-observed-api-version": "v1",
      "kubevirt.io/storage-observed-api-version": "v1"
    },
    "creationTimestamp": "2025-11-21T06:20:56Z",
    "generateName": "kubevirt-evacuation-",
    "generation": 1,
    "labels": {
      "kubevirt.io/vmi-name": "rhel9-1749"
    },
    "name": "kubevirt-evacuation-l2k75",
    "namespace": "vm-ns-3",
    "resourceVersion": "399601260",
    "uid": "646a8f73-91cb-4bdd-8194-87b2a87044fa"
  },
  "spec": {
    "vmiName": "rhel9-1749"
  },
  "status": {
    "migrationState": {
      "completed": true,
      "endTimestamp": "2025-11-21T06:22:02Z",
      "migrationConfiguration": {
        "allowAutoConverge": false,
        "allowPostCopy": false,
        "allowWorkloadDisruption": false,
        "bandwidthPerMigration": "0",
        "completionTimeoutPerGiB": 150,
        "nodeDrainTaintKey": "kubevirt.io/drain",
        "parallelMigrationsPerCluster": 50,
        "parallelOutboundMigrationsPerNode": 10,
        "progressTimeout": 150,
        "unsafeMigrationOverride": false
      },
      "migrationUid": "646a8f73-91cb-4bdd-8194-87b2a87044fa",
      "mode": "PreCopy",
      "sourceNode": "d24-h01-000-r650",
      "sourcePod": "virt-launcher-rhel9-1749-5wnwc",
      "startTimestamp": "2025-11-21T06:21:56Z",
      "targetDirectMigrationNodePorts": {
        "41401": 49152,
        "42485": 0
      },
      "targetNode": "e28-h22-000-r650",
      "targetNodeAddress": "10.130.12.134",
      "targetNodeDomainDetected": true,
      "targetNodeDomainReadyTimestamp": "2025-11-21T06:22:02Z",
      "targetPod": "virt-launcher-rhel9-1749-zlbdq"
    },
    "phase": "Succeeded",
    "phaseTransitionTimestamps": [
      {
        "phase": "Pending",
        "phaseTransitionTimestamp": "2025-11-21T06:20:56Z"
      },
      {
        "phase": "Scheduling",
        "phaseTransitionTimestamp": "2025-11-21T06:21:49Z"
      },
      {
        "phase": "Scheduled",
        "phaseTransitionTimestamp": "2025-11-21T06:21:56Z"
      },
      {
        "phase": "PreparingTarget",
        "phaseTransitionTimestamp": "2025-11-21T06:21:56Z"
      },
      {
        "phase": "TargetReady",
        "phaseTransitionTimestamp": "2025-11-21T06:21:56Z"
      },
      {
        "phase": "Running",
        "phaseTransitionTimestamp": "2025-11-21T06:21:56Z"
      },
      {
        "phase": "Succeeded",
        "phaseTransitionTimestamp": "2025-11-21T06:22:03Z"
      }
    ]
  }
}
