{
  "apiVersion": "kubevirt.io/v1",
  "kind": "VirtualMachineInstanceMigration",
  "metadata": {
    "annotations": {
      "kubevirt.io/evacuationMigration": "d37-h22-000-r660",
      "kubevirt.io/latest-observed-api-version": "v1",
      "kubevirt.io/storage-observed-api-version": "v1"
    },
    "creationTimestamp": "2025-11-20T16:18:43Z",
    "generateName": "kubevirt-evacuation-",
    "generation": 1,
    "labels": {
      "kubevirt.io/vmi-name": "rhel9-14597"
    },
    "name": "kubevirt-evacuation-5qnjf",
    "namespace": "vm-ns-21",
    "resourceVersion": "383536425",
    "uid": "289555bc-db6c-4fef-a8b4-7e2fda5d41f7"
  },
  "spec": {
    "vmiName": "rhel9-14597"
  },
  "status": {
    "migrationState": {
      "completed": true,
      "endTimestamp": "2025-11-20T16:20:56Z",
      "migrationConfiguration": {
        "allowAutoConverge": false,
        "allowPostCopy": false,
        "allowWorkloadDisruption": false,
        "bandwidthPerMigration": "0",
        "completionTimeoutPerGiB": 150,
        "nodeDrainTaintKey": "kubevirt.io/drain",
        "parallelMigrationsPerCluster": 50,
        "parallelOutboundMigrationsPerNode": 10,
        "progressTimeout": 150,
        "unsafeMigrationOverride": false
      },
      "migrationUid": "289555bc-db6c-4fef-a8b4-7e2fda5d41f7",
      "mode": "PreCopy",
      "sourceNode": "d37-h22-000-r660",
      "sourcePod": "virt-launcher-rhel9-14597-qlckm",
      "startTimestamp": "2025-11-20T16:18:59Z",
      "targetDirectMigrationNodePorts": {
        "41297": 0,
        "41989": 49152
      },
      "targetNode": "d37-h18-000-r660",
      "targetNodeAddress": "10.131.84.130",
      "targetNodeDomainDetected": true,
      "targetNodeDomainReadyTimestamp": "2025-11-20T16:20:55Z",
      "targetPod": "virt-launcher-rhel9-14597-b8ms5"
    },
    "phase": "Succeeded",
    "phaseTransitionTimestamps": [
      {
        "phase": "Pending",
        "phaseTransitionTimestamp": "2025-11-20T16:18:43Z"
      },
      {
        "phase": "Scheduling",
        "phaseTransitionTimestamp": "2025-11-20T16:18:53Z"
      },
      {
        "phase": "Scheduled",
        "phaseTransitionTimestamp": "2025-11-20T16:18:59Z"
      },
      {
        "phase": "PreparingTarget",
        "phaseTransitionTimestamp": "2025-11-20T16:18:59Z"
      },
      {
        "phase": "TargetReady",
        "phaseTransitionTimestamp": "2025-11-20T16:18:59Z"
      },
      {
        "phase": "Running",
        "phaseTransitionTimestamp": "2025-11-20T16:18:59Z"
      },
      {
        "phase": "Succeeded",
        "phaseTransitionTimestamp": "2025-11-20T16:20:56Z"
      }
    ]
  }
}
