{
  "apiVersion": "kubevirt.io/v1",
  "kind": "VirtualMachineInstanceMigration",
  "metadata": {
    "annotations": {
      "kubevirt.io/evacuationMigration": "d35-h26-000-r660",
      "kubevirt.io/latest-observed-api-version": "v1",
      "kubevirt.io/storage-observed-api-version": "v1"
    },
    "creationTimestamp": "2025-11-20T14:29:28Z",
    "generateName": "kubevirt-evacuation-",
    "generation": 1,
    "labels": {
      "kubevirt.io/vmi-name": "rhel9-14347"
    },
    "name": "kubevirt-evacuation-r26vw",
    "namespace": "vm-ns-21",
    "resourceVersion": "383117921",
    "uid": "d28c0773-3205-4997-b66b-9212259d7cfd"
  },
  "spec": {
    "vmiName": "rhel9-14347"
  },
  "status": {
    "migrationState": {
      "completed": true,
      "endTimestamp": "2025-11-20T14:31:03Z",
      "migrationConfiguration": {
        "allowAutoConverge": false,
        "allowPostCopy": false,
        "allowWorkloadDisruption": false,
        "bandwidthPerMigration": "0",
        "completionTimeoutPerGiB": 150,
        "nodeDrainTaintKey": "kubevirt.io/drain",
        "parallelMigrationsPerCluster": 50,
        "parallelOutboundMigrationsPerNode": 10,
        "progressTimeout": 150,
        "unsafeMigrationOverride": false
      },
      "migrationUid": "d28c0773-3205-4997-b66b-9212259d7cfd",
      "mode": "PreCopy",
      "sourceNode": "d35-h26-000-r660",
      "sourcePod": "virt-launcher-rhel9-14347-hz5m9",
      "startTimestamp": "2025-11-20T14:29:40Z",
      "targetDirectMigrationNodePorts": {
        "33295": 49152,
        "43077": 0
      },
      "targetNode": "d35-h22-000-r660",
      "targetNodeAddress": "10.131.78.123",
      "targetNodeDomainDetected": true,
      "targetNodeDomainReadyTimestamp": "2025-11-20T14:31:03Z",
      "targetPod": "virt-launcher-rhel9-14347-sk9vs"
    },
    "phase": "Succeeded",
    "phaseTransitionTimestamps": [
      {
        "phase": "Pending",
        "phaseTransitionTimestamp": "2025-11-20T14:29:28Z"
      },
      {
        "phase": "Scheduling",
        "phaseTransitionTimestamp": "2025-11-20T14:29:28Z"
      },
      {
        "phase": "Scheduled",
        "phaseTransitionTimestamp": "2025-11-20T14:29:39Z"
      },
      {
        "phase": "PreparingTarget",
        "phaseTransitionTimestamp": "2025-11-20T14:29:39Z"
      },
      {
        "phase": "TargetReady",
        "phaseTransitionTimestamp": "2025-11-20T14:29:40Z"
      },
      {
        "phase": "Running",
        "phaseTransitionTimestamp": "2025-11-20T14:29:40Z"
      },
      {
        "phase": "Succeeded",
        "phaseTransitionTimestamp": "2025-11-20T14:31:03Z"
      }
    ]
  }
}
