{
  "apiVersion": "kubevirt.io/v1",
  "kind": "VirtualMachineInstanceMigration",
  "metadata": {
    "annotations": {
      "kubevirt.io/evacuationMigration": "e43-h01-000-r650",
      "kubevirt.io/latest-observed-api-version": "v1",
      "kubevirt.io/storage-observed-api-version": "v1"
    },
    "creationTimestamp": "2025-11-20T23:01:35Z",
    "generateName": "kubevirt-evacuation-",
    "generation": 1,
    "labels": {
      "kubevirt.io/vmi-name": "rhel9-11052"
    },
    "name": "kubevirt-evacuation-z2wvs",
    "namespace": "vm-ns-16",
    "resourceVersion": "388832256",
    "uid": "2062e49a-5e9f-4328-b5c1-96fd6a92fd94"
  },
  "spec": {
    "vmiName": "rhel9-11052"
  },
  "status": {
    "migrationState": {
      "completed": true,
      "endTimestamp": "2025-11-20T23:10:15Z",
      "migrationConfiguration": {
        "allowAutoConverge": false,
        "allowPostCopy": false,
        "allowWorkloadDisruption": false,
        "bandwidthPerMigration": "0",
        "completionTimeoutPerGiB": 150,
        "nodeDrainTaintKey": "kubevirt.io/drain",
        "parallelMigrationsPerCluster": 50,
        "parallelOutboundMigrationsPerNode": 10,
        "progressTimeout": 150,
        "unsafeMigrationOverride": false
      },
      "migrationUid": "2062e49a-5e9f-4328-b5c1-96fd6a92fd94",
      "mode": "PreCopy",
      "sourceNode": "e43-h01-000-r650",
      "sourcePod": "virt-launcher-rhel9-11052-845m4",
      "startTimestamp": "2025-11-20T23:04:03Z",
      "targetDirectMigrationNodePorts": {
        "32923": 0,
        "43465": 49152
      },
      "targetNode": "e42-h34-000-r650",
      "targetNodeAddress": "10.130.68.144",
      "targetNodeDomainDetected": true,
      "targetNodeDomainReadyTimestamp": "2025-11-20T23:10:15Z",
      "targetPod": "virt-launcher-rhel9-11052-698v8"
    },
    "phase": "Succeeded",
    "phaseTransitionTimestamps": [
      {
        "phase": "Pending",
        "phaseTransitionTimestamp": "2025-11-20T23:01:40Z"
      },
      {
        "phase": "Scheduling",
        "phaseTransitionTimestamp": "2025-11-20T23:03:54Z"
      },
      {
        "phase": "Scheduled",
        "phaseTransitionTimestamp": "2025-11-20T23:04:03Z"
      },
      {
        "phase": "PreparingTarget",
        "phaseTransitionTimestamp": "2025-11-20T23:04:03Z"
      },
      {
        "phase": "TargetReady",
        "phaseTransitionTimestamp": "2025-11-20T23:04:03Z"
      },
      {
        "phase": "Running",
        "phaseTransitionTimestamp": "2025-11-20T23:04:03Z"
      },
      {
        "phase": "Succeeded",
        "phaseTransitionTimestamp": "2025-11-20T23:10:15Z"
      }
    ]
  }
}
