{
  "apiVersion": "kubevirt.io/v1",
  "kind": "VirtualMachineInstanceMigration",
  "metadata": {
    "annotations": {
      "kubevirt.io/evacuationMigration": "e45-h02-000-r650",
      "kubevirt.io/latest-observed-api-version": "v1",
      "kubevirt.io/storage-observed-api-version": "v1"
    },
    "creationTimestamp": "2025-11-20T23:54:27Z",
    "generateName": "kubevirt-evacuation-",
    "generation": 1,
    "labels": {
      "kubevirt.io/vmi-name": "rhel9-5615"
    },
    "name": "kubevirt-evacuation-vlcpg",
    "namespace": "vm-ns-9",
    "resourceVersion": "390018905",
    "uid": "34c1f6b6-fb74-472e-bbf3-39f28a907991"
  },
  "spec": {
    "vmiName": "rhel9-5615"
  },
  "status": {
    "migrationState": {
      "completed": true,
      "endTimestamp": "2025-11-20T23:56:40Z",
      "migrationConfiguration": {
        "allowAutoConverge": false,
        "allowPostCopy": false,
        "allowWorkloadDisruption": false,
        "bandwidthPerMigration": "0",
        "completionTimeoutPerGiB": 150,
        "nodeDrainTaintKey": "kubevirt.io/drain",
        "parallelMigrationsPerCluster": 50,
        "parallelOutboundMigrationsPerNode": 10,
        "progressTimeout": 150,
        "unsafeMigrationOverride": false
      },
      "migrationUid": "34c1f6b6-fb74-472e-bbf3-39f28a907991",
      "mode": "PreCopy",
      "sourceNode": "e45-h02-000-r650",
      "sourcePod": "virt-launcher-rhel9-5615-cn8ff",
      "startTimestamp": "2025-11-20T23:56:34Z",
      "targetDirectMigrationNodePorts": {
        "33889": 0,
        "34615": 49152
      },
      "targetNode": "e44-h37-000-r650",
      "targetNodeAddress": "10.129.72.138",
      "targetNodeDomainDetected": true,
      "targetNodeDomainReadyTimestamp": "2025-11-20T23:56:40Z",
      "targetPod": "virt-launcher-rhel9-5615-bgs8j"
    },
    "phase": "Succeeded",
    "phaseTransitionTimestamps": [
      {
        "phase": "Pending",
        "phaseTransitionTimestamp": "2025-11-20T23:54:27Z"
      },
      {
        "phase": "Scheduling",
        "phaseTransitionTimestamp": "2025-11-20T23:56:20Z"
      },
      {
        "phase": "Scheduled",
        "phaseTransitionTimestamp": "2025-11-20T23:56:33Z"
      },
      {
        "phase": "PreparingTarget",
        "phaseTransitionTimestamp": "2025-11-20T23:56:33Z"
      },
      {
        "phase": "TargetReady",
        "phaseTransitionTimestamp": "2025-11-20T23:56:34Z"
      },
      {
        "phase": "Running",
        "phaseTransitionTimestamp": "2025-11-20T23:56:34Z"
      },
      {
        "phase": "Succeeded",
        "phaseTransitionTimestamp": "2025-11-20T23:56:40Z"
      }
    ]
  }
}
