{
  "apiVersion": "kubevirt.io/v1",
  "kind": "VirtualMachineInstanceMigration",
  "metadata": {
    "annotations": {
      "kubevirt.io/evacuationMigration": "d24-h09-000-r650",
      "kubevirt.io/latest-observed-api-version": "v1",
      "kubevirt.io/storage-observed-api-version": "v1"
    },
    "creationTimestamp": "2025-11-20T05:49:00Z",
    "generateName": "kubevirt-evacuation-",
    "generation": 1,
    "labels": {
      "kubevirt.io/vmi-name": "rhel9-70"
    },
    "name": "kubevirt-evacuation-45fkg",
    "namespace": "vm-ns-1",
    "resourceVersion": "381088811",
    "uid": "c7a74ec3-acc2-4a53-9ecc-611fcff3936b"
  },
  "spec": {
    "vmiName": "rhel9-70"
  },
  "status": {
    "migrationState": {
      "completed": true,
      "endTimestamp": "2025-11-20T05:50:39Z",
      "migrationConfiguration": {
        "allowAutoConverge": false,
        "allowPostCopy": false,
        "allowWorkloadDisruption": false,
        "bandwidthPerMigration": "0",
        "completionTimeoutPerGiB": 150,
        "nodeDrainTaintKey": "kubevirt.io/drain",
        "parallelMigrationsPerCluster": 50,
        "parallelOutboundMigrationsPerNode": 10,
        "progressTimeout": 150,
        "unsafeMigrationOverride": false
      },
      "migrationUid": "c7a74ec3-acc2-4a53-9ecc-611fcff3936b",
      "mode": "PreCopy",
      "sourceNode": "d24-h09-000-r650",
      "sourcePod": "virt-launcher-rhel9-70-ks5bk",
      "startTimestamp": "2025-11-20T05:49:05Z",
      "targetDirectMigrationNodePorts": {
        "38715": 0,
        "43601": 49152
      },
      "targetNode": "d24-h03-000-r650",
      "targetNodeAddress": "10.131.2.128",
      "targetNodeDomainDetected": true,
      "targetNodeDomainReadyTimestamp": "2025-11-20T05:50:39Z",
      "targetPod": "virt-launcher-rhel9-70-2xtq6"
    },
    "phase": "Succeeded",
    "phaseTransitionTimestamps": [
      {
        "phase": "Pending",
        "phaseTransitionTimestamp": "2025-11-20T05:49:00Z"
      },
      {
        "phase": "Scheduling",
        "phaseTransitionTimestamp": "2025-11-20T05:49:00Z"
      },
      {
        "phase": "Scheduled",
        "phaseTransitionTimestamp": "2025-11-20T05:49:05Z"
      },
      {
        "phase": "PreparingTarget",
        "phaseTransitionTimestamp": "2025-11-20T05:49:05Z"
      },
      {
        "phase": "TargetReady",
        "phaseTransitionTimestamp": "2025-11-20T05:49:05Z"
      },
      {
        "phase": "Running",
        "phaseTransitionTimestamp": "2025-11-20T05:49:05Z"
      },
      {
        "phase": "Succeeded",
        "phaseTransitionTimestamp": "2025-11-20T05:50:39Z"
      }
    ]
  }
}
