{
  "apiVersion": "kubevirt.io/v1",
  "kind": "VirtualMachineInstanceMigration",
  "metadata": {
    "annotations": {
      "kubevirt.io/evacuationMigration": "d27-h28-000-r650",
      "kubevirt.io/latest-observed-api-version": "v1",
      "kubevirt.io/storage-observed-api-version": "v1"
    },
    "creationTimestamp": "2025-11-20T10:45:54Z",
    "generateName": "kubevirt-evacuation-",
    "generation": 1,
    "labels": {
      "kubevirt.io/vmi-name": "rhel9-22"
    },
    "name": "kubevirt-evacuation-c6447",
    "namespace": "vm-ns-1",
    "resourceVersion": "382276651",
    "uid": "540c738f-a3bf-4a57-95f0-f856cfc01a92"
  },
  "spec": {
    "vmiName": "rhel9-22"
  },
  "status": {
    "migrationState": {
      "completed": true,
      "endTimestamp": "2025-11-20T10:46:13Z",
      "migrationConfiguration": {
        "allowAutoConverge": false,
        "allowPostCopy": false,
        "allowWorkloadDisruption": false,
        "bandwidthPerMigration": "0",
        "completionTimeoutPerGiB": 150,
        "nodeDrainTaintKey": "kubevirt.io/drain",
        "parallelMigrationsPerCluster": 50,
        "parallelOutboundMigrationsPerNode": 10,
        "progressTimeout": 150,
        "unsafeMigrationOverride": false
      },
      "migrationUid": "540c738f-a3bf-4a57-95f0-f856cfc01a92",
      "mode": "PreCopy",
      "sourceNode": "d27-h28-000-r650",
      "sourcePod": "virt-launcher-rhel9-22-b6bxh",
      "startTimestamp": "2025-11-20T10:46:03Z",
      "targetDirectMigrationNodePorts": {
        "34257": 0,
        "36755": 49152
      },
      "targetNode": "d27-h23-000-r650",
      "targetNodeAddress": "10.130.40.129",
      "targetNodeDomainDetected": true,
      "targetNodeDomainReadyTimestamp": "2025-11-20T10:46:13Z",
      "targetPod": "virt-launcher-rhel9-22-kggt4"
    },
    "phase": "Succeeded",
    "phaseTransitionTimestamps": [
      {
        "phase": "Pending",
        "phaseTransitionTimestamp": "2025-11-20T10:45:54Z"
      },
      {
        "phase": "Scheduling",
        "phaseTransitionTimestamp": "2025-11-20T10:45:54Z"
      },
      {
        "phase": "Scheduled",
        "phaseTransitionTimestamp": "2025-11-20T10:46:03Z"
      },
      {
        "phase": "PreparingTarget",
        "phaseTransitionTimestamp": "2025-11-20T10:46:03Z"
      },
      {
        "phase": "TargetReady",
        "phaseTransitionTimestamp": "2025-11-20T10:46:03Z"
      },
      {
        "phase": "Running",
        "phaseTransitionTimestamp": "2025-11-20T10:46:03Z"
      },
      {
        "phase": "Succeeded",
        "phaseTransitionTimestamp": "2025-11-20T10:46:13Z"
      }
    ]
  }
}
