{
  "apiVersion": "kubevirt.io/v1",
  "kind": "VirtualMachineInstanceMigration",
  "metadata": {
    "annotations": {
      "kubevirt.io/evacuationMigration": "e34-h10-000-r650",
      "kubevirt.io/latest-observed-api-version": "v1",
      "kubevirt.io/storage-observed-api-version": "v1"
    },
    "creationTimestamp": "2025-11-20T20:59:29Z",
    "generateName": "kubevirt-evacuation-",
    "generation": 1,
    "labels": {
      "kubevirt.io/vmi-name": "rhel9-4350"
    },
    "name": "kubevirt-evacuation-tkwbb",
    "namespace": "vm-ns-7",
    "resourceVersion": "385540260",
    "uid": "7ed486da-35cf-4f6a-86f4-2a296ad8219d"
  },
  "spec": {
    "vmiName": "rhel9-4350"
  },
  "status": {
    "migrationState": {
      "completed": true,
      "endTimestamp": "2025-11-20T21:00:40Z",
      "migrationConfiguration": {
        "allowAutoConverge": false,
        "allowPostCopy": false,
        "allowWorkloadDisruption": false,
        "bandwidthPerMigration": "0",
        "completionTimeoutPerGiB": 150,
        "nodeDrainTaintKey": "kubevirt.io/drain",
        "parallelMigrationsPerCluster": 50,
        "parallelOutboundMigrationsPerNode": 10,
        "progressTimeout": 150,
        "unsafeMigrationOverride": false
      },
      "migrationUid": "7ed486da-35cf-4f6a-86f4-2a296ad8219d",
      "mode": "PreCopy",
      "sourceNode": "e34-h10-000-r650",
      "sourcePod": "virt-launcher-rhel9-4350-h4rqk",
      "startTimestamp": "2025-11-20T21:00:34Z",
      "targetDirectMigrationNodePorts": {
        "35299": 0,
        "38203": 49152
      },
      "targetNode": "e34-h11-000-r650",
      "targetNodeAddress": "10.128.62.163",
      "targetNodeDomainDetected": true,
      "targetNodeDomainReadyTimestamp": "2025-11-20T21:00:40Z",
      "targetPod": "virt-launcher-rhel9-4350-7dmh6"
    },
    "phase": "Succeeded",
    "phaseTransitionTimestamps": [
      {
        "phase": "Pending",
        "phaseTransitionTimestamp": "2025-11-20T20:59:29Z"
      },
      {
        "phase": "Scheduling",
        "phaseTransitionTimestamp": "2025-11-20T21:00:22Z"
      },
      {
        "phase": "Scheduled",
        "phaseTransitionTimestamp": "2025-11-20T21:00:34Z"
      },
      {
        "phase": "PreparingTarget",
        "phaseTransitionTimestamp": "2025-11-20T21:00:34Z"
      },
      {
        "phase": "TargetReady",
        "phaseTransitionTimestamp": "2025-11-20T21:00:34Z"
      },
      {
        "phase": "Running",
        "phaseTransitionTimestamp": "2025-11-20T21:00:34Z"
      },
      {
        "phase": "Succeeded",
        "phaseTransitionTimestamp": "2025-11-20T21:00:40Z"
      }
    ]
  }
}
