{
  "apiVersion": "kubevirt.io/v1",
  "kind": "VirtualMachineInstanceMigration",
  "metadata": {
    "annotations": {
      "kubevirt.io/evacuationMigration": "d22-h01-000-r650",
      "kubevirt.io/latest-observed-api-version": "v1",
      "kubevirt.io/storage-observed-api-version": "v1"
    },
    "creationTimestamp": "2025-11-20T08:20:10Z",
    "generateName": "kubevirt-evacuation-",
    "generation": 1,
    "labels": {
      "kubevirt.io/vmi-name": "rhel9-11349"
    },
    "name": "kubevirt-evacuation-xq54r",
    "namespace": "vm-ns-17",
    "resourceVersion": "381720844",
    "uid": "f1d5e0ef-fb47-4d88-8d4d-4de346802559"
  },
  "spec": {
    "vmiName": "rhel9-11349"
  },
  "status": {
    "migrationState": {
      "completed": true,
      "endTimestamp": "2025-11-20T08:26:23Z",
      "migrationConfiguration": {
        "allowAutoConverge": false,
        "allowPostCopy": false,
        "allowWorkloadDisruption": false,
        "bandwidthPerMigration": "0",
        "completionTimeoutPerGiB": 150,
        "nodeDrainTaintKey": "kubevirt.io/drain",
        "parallelMigrationsPerCluster": 50,
        "parallelOutboundMigrationsPerNode": 10,
        "progressTimeout": 150,
        "unsafeMigrationOverride": false
      },
      "migrationUid": "f1d5e0ef-fb47-4d88-8d4d-4de346802559",
      "mode": "PreCopy",
      "sourceNode": "d22-h01-000-r650",
      "sourcePod": "virt-launcher-rhel9-11349-rtk9l",
      "startTimestamp": "2025-11-20T08:26:03Z",
      "targetDirectMigrationNodePorts": {
        "33825": 0,
        "37877": 49152
      },
      "targetNode": "d21-h25-000-r650",
      "targetNodeAddress": "10.131.20.131",
      "targetNodeDomainDetected": true,
      "targetNodeDomainReadyTimestamp": "2025-11-20T08:26:23Z",
      "targetPod": "virt-launcher-rhel9-11349-vmkfm"
    },
    "phase": "Succeeded",
    "phaseTransitionTimestamps": [
      {
        "phase": "Pending",
        "phaseTransitionTimestamp": "2025-11-20T08:20:10Z"
      },
      {
        "phase": "Scheduling",
        "phaseTransitionTimestamp": "2025-11-20T08:25:56Z"
      },
      {
        "phase": "Scheduled",
        "phaseTransitionTimestamp": "2025-11-20T08:26:03Z"
      },
      {
        "phase": "PreparingTarget",
        "phaseTransitionTimestamp": "2025-11-20T08:26:03Z"
      },
      {
        "phase": "TargetReady",
        "phaseTransitionTimestamp": "2025-11-20T08:26:03Z"
      },
      {
        "phase": "Running",
        "phaseTransitionTimestamp": "2025-11-20T08:26:03Z"
      },
      {
        "phase": "Succeeded",
        "phaseTransitionTimestamp": "2025-11-20T08:26:23Z"
      }
    ]
  }
}
