{
  "apiVersion": "kubevirt.io/v1",
  "kind": "VirtualMachineInstanceMigration",
  "metadata": {
    "annotations": {
      "kubevirt.io/evacuationMigration": "d27-h31-000-r650",
      "kubevirt.io/latest-observed-api-version": "v1",
      "kubevirt.io/storage-observed-api-version": "v1"
    },
    "creationTimestamp": "2025-11-20T11:56:14Z",
    "generateName": "kubevirt-evacuation-",
    "generation": 1,
    "labels": {
      "kubevirt.io/vmi-name": "rhel9-11613"
    },
    "name": "kubevirt-evacuation-gdj2p",
    "namespace": "vm-ns-17",
    "resourceVersion": "382516153",
    "uid": "501cd15d-e525-4324-ac9a-37f41d731f49"
  },
  "spec": {
    "vmiName": "rhel9-11613"
  },
  "status": {
    "migrationState": {
      "completed": true,
      "endTimestamp": "2025-11-20T11:56:31Z",
      "migrationConfiguration": {
        "allowAutoConverge": false,
        "allowPostCopy": false,
        "allowWorkloadDisruption": false,
        "bandwidthPerMigration": "0",
        "completionTimeoutPerGiB": 150,
        "nodeDrainTaintKey": "kubevirt.io/drain",
        "parallelMigrationsPerCluster": 50,
        "parallelOutboundMigrationsPerNode": 10,
        "progressTimeout": 150,
        "unsafeMigrationOverride": false
      },
      "migrationUid": "501cd15d-e525-4324-ac9a-37f41d731f49",
      "mode": "PreCopy",
      "sourceNode": "d27-h31-000-r650",
      "sourcePod": "virt-launcher-rhel9-11613-nfcmb",
      "startTimestamp": "2025-11-20T11:56:21Z",
      "targetDirectMigrationNodePorts": {
        "40615": 0,
        "43275": 49152
      },
      "targetNode": "e28-h07-000-r650",
      "targetNodeAddress": "10.129.2.124",
      "targetNodeDomainDetected": true,
      "targetNodeDomainReadyTimestamp": "2025-11-20T11:56:31Z",
      "targetPod": "virt-launcher-rhel9-11613-xk7z7"
    },
    "phase": "Succeeded",
    "phaseTransitionTimestamps": [
      {
        "phase": "Pending",
        "phaseTransitionTimestamp": "2025-11-20T11:56:14Z"
      },
      {
        "phase": "Scheduling",
        "phaseTransitionTimestamp": "2025-11-20T11:56:14Z"
      },
      {
        "phase": "Scheduled",
        "phaseTransitionTimestamp": "2025-11-20T11:56:21Z"
      },
      {
        "phase": "PreparingTarget",
        "phaseTransitionTimestamp": "2025-11-20T11:56:21Z"
      },
      {
        "phase": "TargetReady",
        "phaseTransitionTimestamp": "2025-11-20T11:56:21Z"
      },
      {
        "phase": "Running",
        "phaseTransitionTimestamp": "2025-11-20T11:56:21Z"
      },
      {
        "phase": "Succeeded",
        "phaseTransitionTimestamp": "2025-11-20T11:56:31Z"
      }
    ]
  }
}
