{
  "apiVersion": "kubevirt.io/v1",
  "kind": "VirtualMachineInstanceMigration",
  "metadata": {
    "annotations": {
      "kubevirt.io/evacuationMigration": "e35-h07-000-r650",
      "kubevirt.io/latest-observed-api-version": "v1",
      "kubevirt.io/storage-observed-api-version": "v1"
    },
    "creationTimestamp": "2025-11-20T21:47:34Z",
    "generateName": "kubevirt-evacuation-",
    "generation": 1,
    "labels": {
      "kubevirt.io/vmi-name": "rhel9-14854"
    },
    "name": "kubevirt-evacuation-rdld9",
    "namespace": "vm-ns-22",
    "resourceVersion": "386864623",
    "uid": "7b8de900-f2ad-495c-a848-790c7a8aea27"
  },
  "spec": {
    "vmiName": "rhel9-14854"
  },
  "status": {
    "migrationState": {
      "completed": true,
      "endTimestamp": "2025-11-20T21:52:22Z",
      "migrationConfiguration": {
        "allowAutoConverge": false,
        "allowPostCopy": false,
        "allowWorkloadDisruption": false,
        "bandwidthPerMigration": "0",
        "completionTimeoutPerGiB": 150,
        "nodeDrainTaintKey": "kubevirt.io/drain",
        "parallelMigrationsPerCluster": 50,
        "parallelOutboundMigrationsPerNode": 10,
        "progressTimeout": 150,
        "unsafeMigrationOverride": false
      },
      "migrationUid": "7b8de900-f2ad-495c-a848-790c7a8aea27",
      "mode": "PreCopy",
      "sourceNode": "e35-h07-000-r650",
      "sourcePod": "virt-launcher-rhel9-14854-g46zw",
      "startTimestamp": "2025-11-20T21:52:03Z",
      "targetDirectMigrationNodePorts": {
        "34857": 49152,
        "39719": 0
      },
      "targetNode": "e35-h03-000-r650",
      "targetNodeAddress": "10.131.64.128",
      "targetNodeDomainDetected": true,
      "targetNodeDomainReadyTimestamp": "2025-11-20T21:52:22Z",
      "targetPod": "virt-launcher-rhel9-14854-d9pz4"
    },
    "phase": "Succeeded",
    "phaseTransitionTimestamps": [
      {
        "phase": "Pending",
        "phaseTransitionTimestamp": "2025-11-20T21:47:35Z"
      },
      {
        "phase": "Scheduling",
        "phaseTransitionTimestamp": "2025-11-20T21:51:56Z"
      },
      {
        "phase": "Scheduled",
        "phaseTransitionTimestamp": "2025-11-20T21:52:02Z"
      },
      {
        "phase": "PreparingTarget",
        "phaseTransitionTimestamp": "2025-11-20T21:52:02Z"
      },
      {
        "phase": "TargetReady",
        "phaseTransitionTimestamp": "2025-11-20T21:52:03Z"
      },
      {
        "phase": "Running",
        "phaseTransitionTimestamp": "2025-11-20T21:52:03Z"
      },
      {
        "phase": "Succeeded",
        "phaseTransitionTimestamp": "2025-11-20T21:52:23Z"
      }
    ]
  }
}
