{
  "apiVersion": "kubevirt.io/v1",
  "kind": "VirtualMachineInstanceMigration",
  "metadata": {
    "annotations": {
      "kubevirt.io/evacuationMigration": "d40-h05-000-r660",
      "kubevirt.io/latest-observed-api-version": "v1",
      "kubevirt.io/storage-observed-api-version": "v1"
    },
    "creationTimestamp": "2025-11-20T15:55:26Z",
    "generateName": "kubevirt-evacuation-",
    "generation": 1,
    "labels": {
      "kubevirt.io/vmi-name": "rhel9-6861"
    },
    "name": "kubevirt-evacuation-hmvgq",
    "namespace": "vm-ns-10",
    "resourceVersion": "383461910",
    "uid": "895f716b-8457-4459-9d7c-897432de02a2"
  },
  "spec": {
    "vmiName": "rhel9-6861"
  },
  "status": {
    "migrationState": {
      "completed": true,
      "endTimestamp": "2025-11-20T16:00:19Z",
      "migrationConfiguration": {
        "allowAutoConverge": false,
        "allowPostCopy": false,
        "allowWorkloadDisruption": false,
        "bandwidthPerMigration": "0",
        "completionTimeoutPerGiB": 150,
        "nodeDrainTaintKey": "kubevirt.io/drain",
        "parallelMigrationsPerCluster": 50,
        "parallelOutboundMigrationsPerNode": 10,
        "progressTimeout": 150,
        "unsafeMigrationOverride": false
      },
      "migrationUid": "895f716b-8457-4459-9d7c-897432de02a2",
      "mode": "PreCopy",
      "sourceNode": "d40-h05-000-r660",
      "sourcePod": "virt-launcher-rhel9-6861-q42vt",
      "startTimestamp": "2025-11-20T15:59:04Z",
      "targetDirectMigrationNodePorts": {
        "38649": 0,
        "40799": 49152
      },
      "targetNode": "d36-h22-000-r660",
      "targetNodeAddress": "10.129.84.125",
      "targetNodeDomainDetected": true,
      "targetNodeDomainReadyTimestamp": "2025-11-20T16:00:19Z",
      "targetPod": "virt-launcher-rhel9-6861-44fsz"
    },
    "phase": "Succeeded",
    "phaseTransitionTimestamps": [
      {
        "phase": "Pending",
        "phaseTransitionTimestamp": "2025-11-20T15:55:26Z"
      },
      {
        "phase": "Scheduling",
        "phaseTransitionTimestamp": "2025-11-20T15:58:55Z"
      },
      {
        "phase": "Scheduled",
        "phaseTransitionTimestamp": "2025-11-20T15:59:04Z"
      },
      {
        "phase": "PreparingTarget",
        "phaseTransitionTimestamp": "2025-11-20T15:59:04Z"
      },
      {
        "phase": "TargetReady",
        "phaseTransitionTimestamp": "2025-11-20T15:59:04Z"
      },
      {
        "phase": "Running",
        "phaseTransitionTimestamp": "2025-11-20T15:59:04Z"
      },
      {
        "phase": "Succeeded",
        "phaseTransitionTimestamp": "2025-11-20T16:00:20Z"
      }
    ]
  }
}
